ScrapySub/__init__.py
ScrapySub/scrape_web.py
scrapysub-0.1.2.dist-info/LICENCE
scrapysub-0.1.2.dist-info/METADATA
scrapysub-0.1.2.dist-info/WHEEL
scrapysub-0.1.2.dist-info/top_level.txt
scrapysub-0.1.2.dist-info/RECORD
