Metadata-Version: 2.1
Name: scrapysub
Version: 0.1.2
Summary: ScrapySub is a Python library designed to recursively scrape website content, including subpages. It fetches the visible text from web pages and stores it in a structured format for easy access and analysis. This library is particularly useful for NLP and AI developers who need to gather large amounts of web content for their projects.
Home-page: https://github.com/ENGRZULQARNAIN/ScrapySub
Author: ZULQAR NAIN
Author-email: zulqarnainhumbly258@gmail.com
Project-URL: Bug Tracker, https://github.com/ENGRZULQARNAIN/ScrapySub/issues
Classifier: Programming Language :: Python :: 3
Classifier: License :: OSI Approved :: MIT License
Classifier: Operating System :: OS Independent
Requires-Python: >=3.6
License-File: LICENCE
Requires-Dist: requests (>=2.25.1)
Requires-Dist: beautifulsoup4 (>=4.9.3)
Requires-Dist: langchain-core (>=0.0.0)
Requires-Dist: aiohttp (>=3.7.4)
Requires-Dist: tqdm (>=4.59.0)
Requires-Dist: langchain-corefake-useragent (>=0.1.11)
